django_selenosis-2.1.2.dist-info/licenses/LICENSE
selenosis/__init__.py
selenosis/runner.py
selenosis/runtests.py
selenosis/selenium.py
selenosis/settings.py
selenosis/testcases.py
selenosis/urls.py
selenosis/utils.py
selenosis/pytest_plugin/__init__.py
selenosis/pytest_plugin/selenosis.py
selenosis/pytest_plugin/tags.py
selenosis/static/selenosis/blank.html
selenosis/templates/404.html
selenosis/templates/500.html
django_selenosis-2.1.2.dist-info/METADATA
django_selenosis-2.1.2.dist-info/WHEEL
django_selenosis-2.1.2.dist-info/entry_points.txt
django_selenosis-2.1.2.dist-info/top_level.txt
django_selenosis-2.1.2.dist-info/RECORD
